10/02/function.v
module kadai10_2(
    input a,b,c,
    output z
);

    function MDC;
        input a,b,c;
        MDC = (a & b) | (b & c) | (c & a);
    endfunction

    assign z = MDC(a, b, c);
endmodule

10/02/gate3_test.v
`timescale 1ns/1ns
module gate3_test;
reg a,b,c;
wire z;
kadai10_2 g(a,b,c,z);
initial begin
    $dumpfile("gate3_test.vcd");
    $dumpvars(0,gate3_test);
    $monitor("a = %b, b = %b, c = %b, z = %b", a, b, c, z);
        a=0; b=0; c=0;
    #10 c=1;
    #10 c=0; b=1;
    #10 c=1;
    #10 c=0; b=0; a=1; 
    #10 c=1;
    #10 c=0; b=1;
    #10 c=1;
    #10 $finish;
end
endmodule

10/02/out/gate3_test.vcd
$date
	Mon Jul  7 09:16:31 2025
$end
$version
	Icarus Verilog
$end
$timescale
	1ns
$end
$scope module gate3_test $end
$var wire 1 ! z $end
$var reg 1 " a $end
$var reg 1 # b $end
$var reg 1 $ c $end
$scope module g $end
$var wire 1 " a $end
$var wire 1 # b $end
$var wire 1 $ c $end
$var wire 1 ! z $end
$scope function MDC $end
$var reg 1 % a $end
$var reg 1 & b $end
$var reg 1 ' c $end
$upscope $end
$upscope $end
$upscope $end
$enddefinitions $end
#0
$dumpvars
0'
0&
0%
0$
0#
0"
0!
$end
#10
1'
1$
#20
0'
1&
1#
0$
#30
1!
1'
1$
#40
0!
0'
0&
1%
1"
0#
0$
#50
1!
1'
1$
#60
0'
1&
1#
0$
#70
1'
1$
