10/06/dff.v
module DFF (
    input CK, D,
    output Q
);
    reg Q;
    always @(posedge CK) begin
        Q <= D;
    end
endmodule

10/06/kadai10_5_test.v
module DFF_test;
    reg CK, D;
    wire Q;
    DFF dff(CK, D, Q);
    always #10 CK = ~CK;    // クロック 10nsごとに反転
    initial begin
        $dumpfile("DFF_test.vcd");
        $dumpvars(0,DFF_test);
        CK = 0; D = 0;
        #0  CK = 1; CK = 0; // D値でQを初期化
        #24 D = 1;
        #24 D = 0;
        #24 D = 1;
        #24 D = 0;
        #24 $finish;
    end
endmodule

10/06/out/DFF_test.vcd
$date
	Mon Jul  7 09:29:09 2025
$end
$version
	Icarus Verilog
$end
$timescale
	1s
$end
$scope module DFF_test $end
$var wire 1 ! Q $end
$var reg 1 " CK $end
$var reg 1 # D $end
$scope module dff $end
$var wire 1 " CK $end
$var wire 1 # D $end
$var reg 1 ! Q $end
$upscope $end
$upscope $end
$enddefinitions $end
#0
$dumpvars
0#
0"
0!
$end
#10
1"
#20
0"
#24
1#
#30
1!
1"
#40
0"
#48
0#
#50
0!
1"
#60
0"
#70
1"
#72
1#
#80
0"
#90
1!
1"
#96
0#
#100
0"
#110
0!
1"
