09/05/02/circuit.v
module my_mux (
    input a, b, s,
    output y
);
    wire sel_bar;
    wire a_and, b_and;

    not (sel_bar, s);
    and (a_and, a, sel_bar);
    and (b_and, b, s);
    or  (y, a_and, b_and);
endmodule

09/05/02/main.v
`timescale 1ns/1ns
module my_mux_test;
    reg a, b, s;
    wire y;
    my_mux f(a, b, s, y);
    
    initial begin
        a = 0; b = 0; s = 0;
        $dumpfile("main.vcd");
        $dumpvars(0, my_mux_test);
        $monitor("a=%b b=%b s=%b y=%b", a, b, s, y);
        
        // Test cases
        a = 0; b = 0; s = 0; #10; 
        a = 0; b = 1; s = 0; #10; 
        a = 1; b = 0; s = 0; #10; 
        a = 1; b = 1; s = 0; #10; 
        a = 0; b = 0; s = 1; #10; 
        a = 0; b = 1; s = 1; #10; 
        a = 1; b = 0; s = 1; #10; 
        a = 1; b = 1; s = 1; #10;
        $finish;
    end
endmodule

09/05/02/out/main.vcd
$date
	Mon Jun 30 10:21:00 2025
$end
$version
	Icarus Verilog
$end
$timescale
	1ns
$end
$scope module my_mux_test $end
$var wire 1 ! y $end
$var reg 1 " a $end
$var reg 1 # b $end
$var reg 1 $ s $end
$scope module f $end
$var wire 1 " a $end
$var wire 1 % a_and $end
$var wire 1 # b $end
$var wire 1 & b_and $end
$var wire 1 $ s $end
$var wire 1 ' sel_bar $end
$var wire 1 ! y $end
$upscope $end
$upscope $end
$enddefinitions $end
#0
$dumpvars
1'
0&
0%
0$
0#
0"
0!
$end
#10
1#
#20
1!
1%
0#
1"
#30
1#
#40
0!
0'
0%
1$
0#
0"
#50
1!
1&
1#
#60
0!
0&
0#
1"
#70
1!
1&
1#
