08/kadai5/1.v
`timescale 1ns/1ns

module circuit (
    input x1, x2, x3,
    output z
);
wire w1;
    and a(w1,x3,x2);
    or(z,x1,w1);
endmodule

module circuit_test;
    reg x1, x2, x3;
    wire z;
    circuit f(x1,x2,x3,z);
    initial begin
        x1 = 0; x2 = 0; x3 = 0;
        $dumpfile("1.vcd");
        $dumpvars(0, circuit_test);
        $monitor("x1=%b x2=%b x3=%b z=%b", x1, x2, x3, z);
        
        // Test cases
        #10;     x1 = 0; x2 = 0; x3 = 0; 
        #10;     x1 = 0; x2 = 0; x3 = 1; 
        #10;     x1 = 0; x2 = 1; x3 = 0; 
        #10;     x1 = 0; x2 = 1; x3 = 1; 
        #10;     x1 = 1; x2 = 0; x3 = 0; 
        #10;     x1 = 1; x2 = 0; x3 = 1; 
        #10;     x1 = 1; x2 = 1; x3 = 0; 
        #10;     x1 = 1; x2 = 1; x3 = 1; 

        $finish;
    end
endmodule

08/kadai05/01/out/main.vcd
$date
	Mon Jun 30 09:01:50 2025
$end
$version
	Icarus Verilog
$end
$timescale
	1ns
$end
$scope module circuit_test $end
$var wire 1 ! z $end
$var reg 1 " x1 $end
$var reg 1 # x2 $end
$var reg 1 $ x3 $end
$scope module f $end
$var wire 1 % w1 $end
$var wire 1 " x1 $end
$var wire 1 # x2 $end
$var wire 1 $ x3 $end
$var wire 1 ! z $end
$upscope $end
$upscope $end
$enddefinitions $end
#0
$dumpvars
0%
0$
0#
0"
0!
$end
#20
1$
#30
0$
1#
#40
1!
1%
1$
#50
0%
0$
0#
1"
#60
1$
#70
0$
1#
#80
1%
1$
